fastddd/__init__.py
fastddd/errors/app/__init__.py
fastddd/errors/app/base.py
fastddd/errors/app/domain.py
fastddd/errors/app/usecase.py
fastddd/errors/db/__init__.py
fastddd/exc_handlers/psycopg2/__init__.py
fastddd/libs/__init__.py
fastddd/libs/id.py
fastddd/libs/pydantic_validation_handler.py
fastddd/libs/secret.py
fastddd/libs/time.py
fastddd/resources/__init__.py
fastddd/resources/entity.py
fastddd/resources/i_base_repository.py
fastddd/resources/sqlalchemy_repository.py
fastddd/resources/value_object.py
fastddd-0.4.1.dist-info/LICENSE
fastddd-0.4.1.dist-info/METADATA
fastddd-0.4.1.dist-info/WHEEL
fastddd-0.4.1.dist-info/RECORD
